LICENSE
MANIFEST.in
OpenSees-LICENSE
README.rst
requirements.txt
setup.cfg
setup.py
o3plot/__about__.py
o3plot/__init__.py
o3plot/color_grid.py
o3plot/fns.py
o3plot/models.py
o3plot/models_data.dat
o3plot/plotter.py
o3plot/tools.py
o3plot.egg-info/PKG-INFO
o3plot.egg-info/SOURCES.txt
o3plot.egg-info/dependency_links.txt
o3plot.egg-info/not-zip-safe
o3plot.egg-info/requires.txt
o3plot.egg-info/top_level.txt