Metadata-Version: 2.1
Name: o3plot
Version: 0.0.8
Summary: A plotting library for o3seespy
Home-page: UNKNOWN
Author: Maxim Millen
Author-email: mmi46@uclive.ac.nz
License: MIT with OpenSees License
Platform: UNKNOWN
Classifier: Development Status :: 3 - Alpha
Classifier: Intended Audience :: Science/Research
Classifier: Topic :: Scientific/Engineering
Classifier: Programming Language :: Python :: 3
Requires-Python: >=3
Provides-Extra: test
License-File: LICENSE
